ms_validator/__init__.py
ms_validator/param_validation.py
ms_validator_temp-0.0.1a1.dist-info/METADATA
ms_validator_temp-0.0.1a1.dist-info/WHEEL
ms_validator_temp-0.0.1a1.dist-info/top_level.txt
ms_validator_temp-0.0.1a1.dist-info/RECORD
