Metadata-Version: 2.4
Name: ms_validator_temp
Version: 0.0.1a1
Summary: A package for validating .
Author: Jiwang Liu
Requires-Python: >=3.8
